rlm/__init__.py
rlm/backends/__init__.py
rlm/backends/base.py
rlm/backends/litellm.py
rlm/cli/__init__.py
rlm/cli/main.py
rlm/core/__init__.py
rlm/core/config.py
rlm/core/exceptions.py
rlm/core/orchestrator.py
rlm/core/pricing.py
rlm/core/types.py
rlm/logging/__init__.py
rlm/logging/trajectory.py
rlm/mcp/__init__.py
rlm/mcp/auth.py
rlm/mcp/server.py
rlm/repl/__init__.py
rlm/repl/base.py
rlm/repl/docker.py
rlm/repl/local.py
rlm/repl/safety.py
rlm/repl/wasm.py
rlm/tools/__init__.py
rlm/tools/base.py
rlm/tools/registry.py
rlm/tools/builtin/__init__.py
rlm/visualizer/__init__.py
rlm/visualizer/app.py
rlm_runtime-2.0.0.dist-info/METADATA
rlm_runtime-2.0.0.dist-info/WHEEL
rlm_runtime-2.0.0.dist-info/entry_points.txt
rlm_runtime-2.0.0.dist-info/licenses/LICENSE
rlm_runtime-2.0.0.dist-info/RECORD
