Metadata-Version: 2.1
Name: rlm-runtime
Version: 2.0.0
Summary: Recursive Language Model runtime with sandboxed REPL execution
Author-email: Snipara <hello@snipara.com>
License-Expression: Apache-2.0
License-File: LICENSE
Keywords: agents,ai,llm,mcp,recursive,repl
Classifier: Development Status :: 4 - Beta
Classifier: Intended Audience :: Developers
Classifier: License :: OSI Approved :: Apache Software License
Classifier: Programming Language :: Python :: 3.10
Classifier: Programming Language :: Python :: 3.11
Classifier: Programming Language :: Python :: 3.12
Classifier: Topic :: Scientific/Engineering :: Artificial Intelligence
Requires-Python: >=3.10
Requires-Dist: anyio>=4.2.0
Requires-Dist: httpx>=0.27.0
Requires-Dist: litellm>=1.50.0
Requires-Dist: pydantic-settings>=2.1.0
Requires-Dist: pydantic>=2.5.0
Requires-Dist: restrictedpython>=7.1
Requires-Dist: rich>=13.7.0
Requires-Dist: structlog>=24.1.0
Requires-Dist: typer>=0.12.0
Provides-Extra: all
Requires-Dist: rlm-runtime[dev,docker,mcp,snipara,visualizer,wasm]; extra == 'all'
Provides-Extra: dev
Requires-Dist: docker>=7.0.0; extra == 'dev'
Requires-Dist: mcp>=1.0.0; extra == 'dev'
Requires-Dist: mypy>=1.8.0; extra == 'dev'
Requires-Dist: plotly>=5.18.0; extra == 'dev'
Requires-Dist: pytest-asyncio>=0.23.0; extra == 'dev'
Requires-Dist: pytest-cov>=4.1.0; extra == 'dev'
Requires-Dist: pytest>=8.0.0; extra == 'dev'
Requires-Dist: ruff>=0.2.0; extra == 'dev'
Requires-Dist: streamlit>=1.30.0; extra == 'dev'
Provides-Extra: docker
Requires-Dist: docker>=7.0.0; extra == 'docker'
Provides-Extra: mcp
Requires-Dist: mcp>=1.0.0; extra == 'mcp'
Provides-Extra: snipara
Requires-Dist: snipara-mcp>=1.3.0; extra == 'snipara'
Provides-Extra: visualizer
Requires-Dist: plotly>=5.18.0; extra == 'visualizer'
Requires-Dist: streamlit>=1.30.0; extra == 'visualizer'
Provides-Extra: wasm
Requires-Dist: pyodide-py>=0.24.0; extra == 'wasm'
